zamp_public_workflow_sdk/__init__.py
zamp_public_workflow_sdk/actions_hub/__init__.py
zamp_public_workflow_sdk/actions_hub/action_hub_core.py
zamp_public_workflow_sdk/actions_hub/constants.py
zamp_public_workflow_sdk/actions_hub/helper.py
zamp_public_workflow_sdk/actions_hub/models/__init__.py
zamp_public_workflow_sdk/actions_hub/models/activity_models.py
zamp_public_workflow_sdk/actions_hub/models/business_logic_models.py
zamp_public_workflow_sdk/actions_hub/models/common_models.py
zamp_public_workflow_sdk/actions_hub/models/core_models.py
zamp_public_workflow_sdk/actions_hub/models/credentials_models.py
zamp_public_workflow_sdk/actions_hub/models/decorators.py
zamp_public_workflow_sdk/actions_hub/models/mcp_models.py
zamp_public_workflow_sdk/actions_hub/models/workflow_models.py
zamp_public_workflow_sdk/actions_hub/utils/__init__.py
zamp_public_workflow_sdk/actions_hub/utils/context_utils.py
zamp_public_workflow_sdk/actions_hub/utils/datetime_utils.py
zamp_public_workflow_sdk/actions_hub/utils/serializer.py
zamp_public_workflow_sdk/actions_hub/utils/utils.py
zamp_public_workflow_sdk/simulation/__init__.py
zamp_public_workflow_sdk/simulation/activities.py
zamp_public_workflow_sdk/simulation/helper.py
zamp_public_workflow_sdk/simulation/workflow_simulation_service.py
zamp_public_workflow_sdk/simulation/constants/__init__.py
zamp_public_workflow_sdk/simulation/constants/simulation.py
zamp_public_workflow_sdk/simulation/constants/versions.py
zamp_public_workflow_sdk/simulation/models/__init__.py
zamp_public_workflow_sdk/simulation/models/config.py
zamp_public_workflow_sdk/simulation/models/mocked_result.py
zamp_public_workflow_sdk/simulation/models/node_payload.py
zamp_public_workflow_sdk/simulation/models/node_payload_models.py
zamp_public_workflow_sdk/simulation/models/simulation_config_builder.py
zamp_public_workflow_sdk/simulation/models/simulation_fetch_data_workflow.py
zamp_public_workflow_sdk/simulation/models/simulation_response.py
zamp_public_workflow_sdk-0.0.136.dist-info/licenses/LICENCE
zamp_public_workflow_sdk-0.0.136.dist-info/METADATA
zamp_public_workflow_sdk-0.0.136.dist-info/WHEEL
zamp_public_workflow_sdk-0.0.136.dist-info/top_level.txt
zamp_public_workflow_sdk-0.0.136.dist-info/RECORD
