Metadata-Version: 2.4
Name: zamp_public_workflow_sdk
Version: 0.0.136
Summary: Workflow Manager
Home-page: https://github.com/zamp-engineering/workflow_manager
Author: Zamp Engineering
Author-email: engineering@zamp.com
License: MIT
License-File: LICENCE
Requires-Dist: pydantic
Requires-Dist: temporalio==1.13.0
Requires-Dist: python-dateutil
Requires-Dist: python-dotenv
Requires-Dist: sentry-sdk
Requires-Dist: structlog
Dynamic: author
Dynamic: author-email
Dynamic: home-page
Dynamic: license
Dynamic: license-file
Dynamic: requires-dist
Dynamic: summary
